osdatahub/__init__.py
osdatahub/bbox.py
osdatahub/codes.py
osdatahub/errors.py
osdatahub/extent.py
osdatahub/filters.py
osdatahub/grow_list.py
osdatahub/ons_api.py
osdatahub/requests_config.py
osdatahub/requests_wrapper.py
osdatahub/spatial_filter_types.py
osdatahub/utils.py
osdatahub/DownloadsAPI/__init__.py
osdatahub/DownloadsAPI/data_package.py
osdatahub/DownloadsAPI/downloads_api.py
osdatahub/DownloadsAPI/opendata.py
osdatahub/FeaturesAPI/__init__.py
osdatahub/FeaturesAPI/feature_products.py
osdatahub/FeaturesAPI/features_api.py
osdatahub/LinkedIdentifiersAPI/__init__.py
osdatahub/LinkedIdentifiersAPI/linked_identifier_options.py
osdatahub/LinkedIdentifiersAPI/linked_identifiers_api.py
osdatahub/NGD/__init__.py
osdatahub/NGD/crs.py
osdatahub/NGD/ngd_api.py
osdatahub/NamesAPI/__init__.py
osdatahub/NamesAPI/local_types.py
osdatahub/NamesAPI/names_api.py
osdatahub/PlacesAPI/__init__.py
osdatahub/PlacesAPI/places_api.py
osdatahub-1.3.2.dist-info/licenses/LICENSE.txt
osdatahub-1.3.2.dist-info/METADATA
osdatahub-1.3.2.dist-info/WHEEL
osdatahub-1.3.2.dist-info/top_level.txt
osdatahub-1.3.2.dist-info/RECORD
