Metadata-Version: 2.4
Name: osdatahub
Version: 1.3.2
Summary: osdatahub is Ordnance Survey's (OS) Python API wrapper, designed to make data from the OS Data Hub APIs readily accessible to developers.
Home-page: https://github.com/OrdnanceSurvey/osdatahub
Download-URL: https://pypi.org/project/osdatahub/
Author: OS Data Science
Author-email: datascience@os.uk
License: OGL
Project-URL: Code, https://github.com/OrdnanceSurvey/osdatahub
Project-URL: Documentation, https://osdatahub.readthedocs.io/en/latest/
Project-URL: Issues, https://github.com/OrdnanceSurvey/osdatahub/issues
Keywords: Ordnance-Survey,GIS,united-kingdom
Classifier: Natural Language :: English
Classifier: Intended Audience :: Developers
Classifier: Intended Audience :: Science/Research
Classifier: Programming Language :: Python :: 3.10
Classifier: Programming Language :: Python :: 3.11
Classifier: Programming Language :: Python :: 3.12
Classifier: Programming Language :: Python :: 3.13
Classifier: Topic :: Utilities
Classifier: Topic :: Scientific/Engineering :: GIS
Requires-Python: >=3.10
License-File: LICENSE.txt
Requires-Dist: geojson~=3.2.0
Requires-Dist: requests~=2.32.4
Requires-Dist: typeguard~=4.4.4
Requires-Dist: shapely~=2.1.1
Requires-Dist: tqdm~=4.67.1
Requires-Dist: setuptools>=80.9.0
Requires-Dist: urllib3>=2.5.0
Requires-Dist: zipp>=3.23.0
Provides-Extra: dev
Requires-Dist: requests-mock; extra == "dev"
Requires-Dist: pytest; extra == "dev"
Requires-Dist: python-dotenv; extra == "dev"
Provides-Extra: docs
Requires-Dist: sphinx; extra == "docs"
Requires-Dist: sphinx_rtd_theme; extra == "docs"
Requires-Dist: sphinxcontrib-napoleon; extra == "docs"
Requires-Dist: myst-parser; extra == "docs"
Requires-Dist: sphinx-autodocgen; extra == "docs"
Requires-Dist: sphinx-autopackagesummary; extra == "docs"
Dynamic: download-url
Dynamic: license-file
